{
    "score": 0.9405481640030356,
    "keypoints": [
        {
            "score": 0.9764661192893982,
            "part": "nose",
            "position": {
                "x": 259.81768300097275,
                "y": 76.83370639623138
            }
        },
        {
            "score": 0.9457663297653198,
            "part": "leftEye",
            "position": {
                "x": 269.20461454280155,
                "y": 65.70123069644592
            }
        },
        {
            "score": 0.9679640531539917,
            "part": "rightEye",
            "position": {
                "x": 251.10891141780155,
                "y": 60.992763697174546
            }
        },
        {
            "score": 0.3918227553367615,
            "part": "leftEar",
            "position": {
                "x": 277.09869741001944,
                "y": 65.38936318511172
            }
        },
        {
            "score": 0.988326370716095,
            "part": "rightEar",
            "position": {
                "x": 224.02336150291828,
                "y": 53.17838204339378
            }
        },
        {
            "score": 0.991008460521698,
            "part": "leftShoulder",
            "position": {
                "x": 278.40261733949416,
                "y": 118.08311343810719
            }
        },
        {
            "score": 0.9987474679946899,
            "part": "rightShoulder",
            "position": {
                "x": 173.0577235834144,
                "y": 106.26173898963731
            }
        },
        {
            "score": 0.9781560897827148,
            "part": "leftElbow",
            "position": {
                "x": 284.24115013983464,
                "y": 197.64210755343265
            }
        },
        {
            "score": 0.9990382194519043,
            "part": "rightElbow",
            "position": {
                "x": 143.47040673638134,
                "y": 185.63234319340998
            }
        },
        {
            "score": 0.9117697477340698,
            "part": "leftWrist",
            "position": {
                "x": 275.12737110894943,
                "y": 268.49030015382124
            }
        },
        {
            "score": 0.995102047920227,
            "part": "rightWrist",
            "position": {
                "x": 167.1076840649319,
                "y": 250.45814948996113
            }
        },
        {
            "score": 0.9914429187774658,
            "part": "leftHip",
            "position": {
                "x": 233.32426434824902,
                "y": 252.66080391839378
            }
        },
        {
            "score": 0.9989092350006104,
            "part": "rightHip",
            "position": {
                "x": 176.2746040552043,
                "y": 247.01718977695919
            }
        },
        {
            "score": 0.9620699882507324,
            "part": "leftKnee",
            "position": {
                "x": 225.47572273224708,
                "y": 334.4149100348122
            }
        },
        {
            "score": 0.9823827147483826,
            "part": "rightKnee",
            "position": {
                "x": 187.8691178258755,
                "y": 334.6718269308614
            }
        },
        {
            "score": 0.976354718208313,
            "part": "leftAnkle",
            "position": {
                "x": 202.52846090710116,
                "y": 414.03076171875
            }
        },
        {
            "score": 0.933991551399231,
            "part": "rightAnkle",
            "position": {
                "x": 201.01936785627433,
                "y": 415.28043282464375
            }
        }
    ]
}